polyid/__init__.py
polyid/_version.py
polyid/domain_of_validity.py
polyid/parameters.py
polyid/polyid.py
polyid/models/__init__.py
polyid/models/base_models.py
polyid/models/callbacks.py
polyid/models/tacticity_models.py
polyid/preprocessors/__init__.py
polyid/preprocessors/features.py
polyid/preprocessors/preprocessors.py
polyid-0.1.2.3.dist-info/LICENCE.md
polyid-0.1.2.3.dist-info/METADATA
polyid-0.1.2.3.dist-info/WHEEL
polyid-0.1.2.3.dist-info/top_level.txt
polyid-0.1.2.3.dist-info/RECORD
