Metadata-Version: 2.1
Name: polyid
Version: 0.1.2.3
Summary: Methods to train message passing neural network models on polymer structures.
Home-page: https://github.com/NREL/polyid
Author: Kevin Shebek, Nolan Wilson
Author-email: nolan.wilson@nrel.gov
Project-URL: Source, https://github.com/NREL/polyid
Classifier: Development Status :: 3 - Alpha
Classifier: Intended Audience :: Developers
Classifier: License :: OSI Approved :: BSD License
Classifier: Programming Language :: Python :: 3.8
Classifier: Programming Language :: Python :: 3.9
License-File: LICENCE.md
Requires-Dist: pandas
Requires-Dist: rdkit
Requires-Dist: tqdm
Requires-Dist: nfp
Requires-Dist: shortuuid
Requires-Dist: scikit-learn==1.3.0
Requires-Dist: tensorflow>=2
Requires-Dist: m2p
Provides-Extra: test
Requires-Dist: pytest; extra == "test"
